clage_homeserver/__init__.py
clage_homeserver/clage_homeserver.py
tests/__init__.py
tests/test_clage_homeserver.py
tests/test_clage_homeserver_mapper.py
clage_homeserver-0.1.14.dist-info/LICENSE
clage_homeserver-0.1.14.dist-info/METADATA
clage_homeserver-0.1.14.dist-info/WHEEL
clage_homeserver-0.1.14.dist-info/top_level.txt
clage_homeserver-0.1.14.dist-info/RECORD
