Metadata-Version: 2.1
Name: clage-homeserver
Version: 0.1.14
Summary: A Python API for accessing and managing an electrical CLAGE continuous waterheater (e.g. DSX Touch) via the CLAGE Homeserver REST API
Home-page: https://github.com/klacol/clage_homeserver
Author: Klaus Aengenvoort
Classifier: Programming Language :: Python :: 3
Classifier: License :: OSI Approved :: MIT License
Classifier: Operating System :: OS Independent
Provides: clage_homeserver
Requires-Python: >=3.6
License-File: LICENSE
Requires-Dist: requests
